analytics_mcp/__init__.py
analytics_mcp/coordinator.py
analytics_mcp/server.py
analytics_mcp/tools/__init__.py
analytics_mcp/tools/utils.py
analytics_mcp/tools/admin/info.py
analytics_mcp/tools/reporting/__init__.py
analytics_mcp/tools/reporting/core.py
analytics_mcp/tools/reporting/metadata.py
analytics_mcp/tools/reporting/realtime.py
claudiu_analytics_mcp-0.1.1.dist-info/licenses/LICENSE
claudiu_analytics_mcp-0.1.1.dist-info/METADATA
claudiu_analytics_mcp-0.1.1.dist-info/WHEEL
claudiu_analytics_mcp-0.1.1.dist-info/entry_points.txt
claudiu_analytics_mcp-0.1.1.dist-info/top_level.txt
claudiu_analytics_mcp-0.1.1.dist-info/RECORD
