Metadata-Version: 2.4
Name: claudiu-analytics-mcp
Version: 0.1.1
Summary: MCP server for Google Analytics
Author-email: Claudiu Mihaila <iclaudiumihaila@gmail.com>
License-Expression: Apache-2.0
Project-URL: homepage, https://github.com/iclaudiumihaila/google-analytics-mcp
Project-URL: repository, https://github.com/iclaudiumihaila/google-analytics-mcp.git
Project-URL: issues, https://github.com/iclaudiumihaila/google-analytics-mcp/issues
Keywords: google analytics,analytics,mcp,ga4
Classifier: Development Status :: 4 - Beta
Classifier: Intended Audience :: Developers
Classifier: Intended Audience :: End Users/Desktop
Classifier: Programming Language :: Python
Classifier: Programming Language :: Python :: 3.10
Classifier: Programming Language :: Python :: 3.11
Classifier: Programming Language :: Python :: 3.12
Classifier: Programming Language :: Python :: 3.13
Classifier: Operating System :: OS Independent
Classifier: Topic :: Internet
Classifier: Topic :: Scientific/Engineering :: Artificial Intelligence
Classifier: Topic :: Scientific/Engineering :: Information Analysis
Requires-Python: >=3.10
License-File: LICENSE
Requires-Dist: google-analytics-data==0.18.19
Requires-Dist: google-analytics-admin==0.24.1
Requires-Dist: google-auth~=2.40
Requires-Dist: mcp[cli]>=1.2.0
Requires-Dist: httpx>=0.28.1
Provides-Extra: dev
Requires-Dist: black; extra == "dev"
Requires-Dist: nox<2026,>=2025.5.1; extra == "dev"
Dynamic: license-file
